tree_sitter_miniscript/__init__.py
tree_sitter_miniscript/__init__.pyi
tree_sitter_miniscript/_binding.pyd
tree_sitter_miniscript/binding.c
tree_sitter_miniscript/py.typed
tree_sitter_miniscript/queries/highlights.scm
tree_sitter_miniscript/queries/locals.scm
tree_sitter_miniscript-1.0.2.dist-info/METADATA
tree_sitter_miniscript-1.0.2.dist-info/WHEEL
tree_sitter_miniscript-1.0.2.dist-info/top_level.txt
tree_sitter_miniscript-1.0.2.dist-info/RECORD
