Metadata-Version: 2.4
Name: tree-sitter-miniscript
Version: 1.0.2
Summary: Miniscript grammar for tree-sitter
Author-email: Garfieldcmix <chayanon.nin@gmail.com>
License: MIT
Project-URL: Homepage, https://github.com/chayanon-ninyawee/tree-sitter-miniscript
Keywords: incremental,parsing,tree-sitter,miniscript
Classifier: Intended Audience :: Developers
Classifier: Topic :: Software Development :: Compilers
Classifier: Topic :: Text Processing :: Linguistic
Classifier: Typing :: Typed
Requires-Python: >=3.10
Provides-Extra: core
Requires-Dist: tree-sitter~=0.24; extra == "core"
